mend_images_vuln/__init__.py
mend_images_vuln/_version.py
mend_images_vuln/images_vuln.py
mend_images_vuln/mend_api.py
mend_images_vuln/mend_const.py
mend_images_vuln-2023.9.1.dist-info/LICENSE
mend_images_vuln-2023.9.1.dist-info/METADATA
mend_images_vuln-2023.9.1.dist-info/WHEEL
mend_images_vuln-2023.9.1.dist-info/entry_points.txt
mend_images_vuln-2023.9.1.dist-info/top_level.txt
mend_images_vuln-2023.9.1.dist-info/RECORD
