Metadata-Version: 2.1
Name: mend-images-vuln
Version: 2023.9.1
Summary: Get vulnerabilities from Images
Home-page: https://github.com/mend-toolkit/images-vuln
Author: Mend Professional Services
Author-email: ps@mend.io
License: LICENSE.txt
Platform: UNKNOWN
Classifier: Programming Language :: Python :: 3.9
Classifier: Programming Language :: Python :: 3.10
Classifier: Programming Language :: Python :: 3.11
Classifier: License :: OSI Approved :: Apache Software License
Classifier: Operating System :: OS Independent
Requires-Python: >=3.9
License-File: LICENSE
Requires-Dist: requests ~=2.31.0
Requires-Dist: urllib3 ~=2.0.4
